{
  "_class": "shapeGroup",
  "booleanOperation": -1,
  "clippingMaskMode": 0,
  "do_objectID": "9BD48F30-B5B2-4C36-B5E1-EAA44D315D74",
  "exportOptions": {
    "_class": "exportOptions",
    "do_objectID": "4C90D85C-8355-4F3C-B278-FE85AB81AAE7",
    "exportFormats": [
    ],
    "includedLayerIds": [
    ],
    "layerOptions": 0,
    "shouldTrim": false
  },
  "frame": {
    "_class": "rect",
    "constrainProportions": false,
    "do_objectID": "44A71DA4-FE0F-4A2C-92FB-8A8E48A036DB",
    "height": 20,
    "width": 24,
    "x": 0,
    "y": 2
  },
  "groupLayout": {
    "_class": "MSImmutableFreeformGroupLayout",
    "do_objectID": "687C2D50-EACB-43E0-BB27-3DF2CA76443B"
  },
  "hasClickThrough": false,
  "hasClippingMask": false,
  "isFixedToViewport": false,
  "isFlippedHorizontal": false,
  "isFlippedVertical": false,
  "isLocked": false,
  "isVisible": true,
  "layerListExpandedType": 0,
  "layers": [
    {
      "class": "rectangle",
      "id": "F34FF345-996F-45C9-9489-EE60024ADDE9"
    },
    {
      "class": "shapePath",
      "id": "74E68AE8-F715-46B4-A704-9807776FE990"
    },
    {
      "class": "shapePath",
      "id": "35787189-9C9A-40B4-B296-58162C545440"
    }
  ],
  "name": "Shape",
  "nameIsFixed": false,
  "resizingConstraint": 61,
  "resizingType": 0,
  "rotation": 0,
  "sharedStyleID": "0063603B-7CC1-4BCC-A27B-354F02E67EB3",
  "shouldBreakMaskChain": false,
  "style": {
    "_class": "style",
    "do_objectID": "276F797F-5DC1-428D-9E82-8FF1A971C286",
    "endMarkerType": 0,
    "fills": [
      {
        "_class": "fill",
        "color": {
          "_class": "color",
          "alpha": 1,
          "blue": 0.07450980392156861,
          "green": 0.3176470588235294,
          "red": 0.9058823529411765
        },
        "fillType": 0,
        "isEnabled": true,
        "noiseIndex": 0,
        "noiseIntensity": 0,
        "patternFillType": 1,
        "patternTileScale": 1
      }
    ],
    "miterLimit": 10,
    "startMarkerType": 0,
    "windingRule": 0
  },
  "userInfo": {
    "com.animaapp.stc-sketch-plugin": {
      "kModelPropertiesKey": {
      }
    }
  },
  "windingRule": 0
}