{
  "_class": "text",
  "attributedString": {
    "_class": "attributedString",
    "attributes": [
      {
        "_class": "stringAttribute",
        "attributes": {
          "MSAttributedStringColorAttribute": {
            "_class": "color",
            "alpha": 1,
            "blue": 0.4117647058823529,
            "green": 0.05882352941176471,
            "red": 0.9294117647058824
          },
          "MSAttributedStringFontAttribute": {
            "_class": "fontDescriptor",
            "attributes": {
              "name": "OpenSans-Bold",
              "size": 16
            }
          },
          "paragraphStyle": {
            "_class": "paragraphStyle",
            "alignment": 2,
            "baseWritingDirection": 0,
            "headerLevel": 2,
            "maximumLineHeight": 24,
            "minimumLineHeight": 24
          }
        },
        "length": 11,
        "location": 0
      }
    ],
    "string": "Paragraph 1"
  },
  "automaticallyDrawOnUnderlyingPath": false,
  "booleanOperation": -1,
  "clippingMaskMode": 0,
  "do_objectID": "92D9A814-FEB7-4238-A5E0-BE8FD8C022A3",
  "dontSynchroniseWithSymbol": false,
  "exportOptions": {
    "_class": "exportOptions",
    "do_objectID": "588D4EB4-15AD-4C35-9FC0-91168CE4612B",
    "exportFormats": [
    ],
    "includedLayerIds": [
    ],
    "layerOptions": 0,
    "shouldTrim": false
  },
  "frame": {
    "_class": "rect",
    "constrainProportions": false,
    "do_objectID": "F3C11CFF-7B7D-4DC9-AB5B-736C77C086DF",
    "height": 24,
    "width": 96,
    "x": 0,
    "y": 281
  },
  "glyphBounds": "{{1, 5}, {93, 17}}",
  "hasClippingMask": false,
  "isFixedToViewport": false,
  "isFlippedHorizontal": false,
  "isFlippedVertical": false,
  "isLocked": false,
  "isVisible": true,
  "layerListExpandedType": 0,
  "lineSpacingBehaviour": 2,
  "name": "Paragraph_1/mobi/ff#1/center/Pink/--bold",
  "nameIsFixed": false,
  "resizingConstraint": 47,
  "resizingType": 0,
  "rotation": 0,
  "sharedStyleID": "B429F781-B19E-4B42-989C-F9C77B67E14E",
  "shouldBreakMaskChain": false,
  "style": {
    "_class": "style",
    "do_objectID": "22708EFE-11C4-4157-8997-4E3DF8CD347F",
    "endMarkerType": 0,
    "miterLimit": 10,
    "startMarkerType": 0,
    "textStyle": {
      "_class": "textStyle",
      "do_objectID": "2E780B84-2CFE-4662-A3B4-D20F690D501D",
      "encodedAttributes": {
        "MSAttributedStringColorAttribute": {
          "_class": "color",
          "alpha": 1,
          "blue": 0.4117647058823529,
          "green": 0.05882352941176471,
          "red": 0.9294117647058824
        },
        "MSAttributedStringFontAttribute": {
          "_class": "fontDescriptor",
          "attributes": {
            "name": "OpenSans-Bold",
            "size": 16
          }
        },
        "paragraphStyle": {
          "_class": "paragraphStyle",
          "alignment": 2,
          "baseWritingDirection": 0,
          "headerLevel": 2,
          "maximumLineHeight": 24,
          "minimumLineHeight": 24
        }
      },
      "verticalAlignment": 0
    },
    "windingRule": 1
  },
  "textBehaviour": 0
}