{
  "_class": "text",
  "attributedString": {
    "_class": "attributedString",
    "attributes": [
      {
        "_class": "stringAttribute",
        "attributes": {
          "MSAttributedStringColorAttribute": {
            "_class": "color",
            "alpha": 1,
            "blue": 0.4117647058823529,
            "green": 0.05882352941176471,
            "red": 0.9294117647058824
          },
          "MSAttributedStringFontAttribute": {
            "_class": "fontDescriptor",
            "attributes": {
              "name": "OpenSans-Light",
              "size": 28
            }
          },
          "paragraphStyle": {
            "_class": "paragraphStyle",
            "alignment": 0,
            "baseWritingDirection": 0,
            "headerLevel": 2,
            "maximumLineHeight": 40,
            "minimumLineHeight": 40
          }
        },
        "length": 4,
        "location": 0
      }
    ],
    "string": "Hero"
  },
  "automaticallyDrawOnUnderlyingPath": false,
  "booleanOperation": -1,
  "clippingMaskMode": 0,
  "do_objectID": "A11D1771-EED0-44E0-AA0F-91CE8FF069DF",
  "dontSynchroniseWithSymbol": false,
  "exportOptions": {
    "_class": "exportOptions",
    "do_objectID": "207C9DC6-9C3C-46E5-89CD-99C11ADD08B8",
    "exportFormats": [
    ],
    "includedLayerIds": [
    ],
    "layerOptions": 0,
    "shouldTrim": false
  },
  "frame": {
    "_class": "rect",
    "constrainProportions": false,
    "do_objectID": "DAD0192D-83EA-4752-A351-B50F7F785714",
    "height": 40,
    "width": 63,
    "x": 0,
    "y": 64
  },
  "glyphBounds": "{{2, 11}, {59, 21}}",
  "hasClippingMask": false,
  "isFixedToViewport": false,
  "isFlippedHorizontal": false,
  "isFlippedVertical": false,
  "isLocked": false,
  "isVisible": true,
  "layerListExpandedType": 0,
  "lineSpacingBehaviour": 2,
  "name": "Hero/mobi/ff#1/left/Pink/light",
  "nameIsFixed": false,
  "resizingConstraint": 47,
  "resizingType": 0,
  "rotation": 0,
  "sharedStyleID": "93D3809D-D8A7-4D07-B62B-AE70B7E0A701",
  "shouldBreakMaskChain": false,
  "style": {
    "_class": "style",
    "do_objectID": "5B076208-3FF6-4742-9ABC-DB905C16998A",
    "endMarkerType": 0,
    "miterLimit": 10,
    "startMarkerType": 0,
    "textStyle": {
      "_class": "textStyle",
      "do_objectID": "427E4323-A944-4D12-BF09-3FD2532D10A7",
      "encodedAttributes": {
        "MSAttributedStringColorAttribute": {
          "_class": "color",
          "alpha": 1,
          "blue": 0.4117647058823529,
          "green": 0.05882352941176471,
          "red": 0.9294117647058824
        },
        "MSAttributedStringFontAttribute": {
          "_class": "fontDescriptor",
          "attributes": {
            "name": "OpenSans-Light",
            "size": 28
          }
        },
        "paragraphStyle": {
          "_class": "paragraphStyle",
          "alignment": 0,
          "baseWritingDirection": 0,
          "headerLevel": 2,
          "maximumLineHeight": 40,
          "minimumLineHeight": 40
        }
      },
      "verticalAlignment": 0
    },
    "windingRule": 1
  },
  "textBehaviour": 0
}