{
  "_class": "symbolMaster",
  "backgroundColor": {
    "_class": "color",
    "alpha": 1,
    "blue": 1,
    "green": 1,
    "red": 1
  },
  "booleanOperation": -1,
  "changeIdentifier": 4588,
  "clippingMaskMode": 0,
  "do_objectID": "93D1666C-2D75-46D3-A728-E5FF453A5ED8",
  "exportOptions": {
    "_class": "exportOptions",
    "exportFormats": [
    ],
    "includedLayerIds": [
    ],
    "layerOptions": 0,
    "shouldTrim": false
  },
  "frame": {
    "_class": "rect",
    "constrainProportions": false,
    "height": 48,
    "width": 323,
    "x": 743,
    "y": 1038
  },
  "groupLayout": {
    "_class": "MSImmutableFreeformGroupLayout"
  },
  "hasBackgroundColor": false,
  "hasClickThrough": true,
  "hasClippingMask": false,
  "horizontalRulerData": {
    "_class": "rulerData",
    "base": 0,
    "guides": [
    ]
  },
  "includeBackgroundColorInExport": true,
  "includeBackgroundColorInInstance": false,
  "includeInCloudUpload": true,
  "isFixedToViewport": false,
  "isFlippedHorizontal": false,
  "isFlippedVertical": false,
  "isFlowHome": false,
  "isLocked": false,
  "isVisible": true,
  "layerListExpandedType": 0,
  "layers": [
    {
      "class": "symbolInstance",
      "id": "1192A5C9-BE49-44FF-9075-AEB63CCDB470"
    },
    {
      "class": "symbolInstance",
      "id": "BBA2C560-6916-4F44-809F-C7DA71D265EA"
    },
    {
      "class": "symbolInstance",
      "id": "C78D9577-FA05-4701-A3B8-8E80D77FA73E"
    },
    {
      "class": "symbolInstance",
      "id": "34627F7D-6848-4684-974F-EFFD29A1FCEF"
    }
  ],
  "layout": {
    "_class": "layoutGrid",
    "columnWidth": 21.66666666666667,
    "drawHorizontal": true,
    "drawHorizontalLines": true,
    "drawVertical": false,
    "gutterHeight": 8,
    "gutterWidth": 5,
    "guttersOutside": true,
    "horizontalOffset": 0,
    "isEnabled": false,
    "numberOfColumns": 12,
    "rowHeightMultiplication": 5,
    "totalWidth": 320
  },
  "name": "button/desk/txt-center/text+icon",
  "nameIsFixed": true,
  "overrideProperties": [
    {
      "_class": "MSImmutableOverrideProperty",
      "canOverride": true,
      "overrideName": "C78D9577-FA05-4701-A3B8-8E80D77FA73E_symbolID"
    },
    {
      "_class": "MSImmutableOverrideProperty",
      "canOverride": true,
      "overrideName": "BBA2C560-6916-4F44-809F-C7DA71D265EA_symbolID"
    },
    {
      "_class": "MSImmutableOverrideProperty",
      "canOverride": true,
      "overrideName": "34627F7D-6848-4684-974F-EFFD29A1FCEF_symbolID"
    },
    {
      "_class": "MSImmutableOverrideProperty",
      "canOverride": true,
      "overrideName": "1192A5C9-BE49-44FF-9075-AEB63CCDB470_symbolID"
    }
  ],
  "resizesContent": true,
  "resizingConstraint": 63,
  "resizingType": 0,
  "rotation": 0,
  "shouldBreakMaskChain": true,
  "style": {
    "_class": "style",
    "endMarkerType": 0,
    "miterLimit": 10,
    "startMarkerType": 0,
    "windingRule": 1
  },
  "symbolID": "109E0759-52D4-4FE9-8D02-041C2AD75DD3",
  "userInfo": {
    "com.animaapp.stc-sketch-plugin": {
      "kModelPropertiesKey": {
      }
    }
  },
  "verticalRulerData": {
    "_class": "rulerData",
    "base": 0,
    "guides": [
    ]
  }
}