{
  "_class": "sharedStyle",
  "do_objectID": "FBA76CC4-05C1-4F1B-AA12-D3AF49A7E2AF",
  "name": "Paragraph_2/mobi/ff#1/right/High_Grey/-regular",
  "value": {
    "_class": "style",
    "endMarkerType": 0,
    "miterLimit": 10,
    "startMarkerType": 0,
    "textStyle": {
      "_class": "textStyle",
      "encodedAttributes": {
        "MSAttributedStringColorAttribute": {
          "_class": "color",
          "alpha": 1,
          "blue": 0.1843137254901961,
          "green": 0.1843137254901961,
          "red": 0.1843137254901961
        },
        "MSAttributedStringFontAttribute": {
          "_class": "fontDescriptor",
          "attributes": {
            "name": "OpenSans",
            "size": 14
          }
        },
        "paragraphStyle": {
          "_class": "paragraphStyle",
          "alignment": 1,
          "baseWritingDirection": 0,
          "headerLevel": 2,
          "maximumLineHeight": 20,
          "minimumLineHeight": 20
        }
      },
      "verticalAlignment": 0
    },
    "windingRule": 1
  }
}